nonebot_plugin_bilifan/__init__.py
nonebot_plugin_bilifan/main.py
nonebot_plugin_bilifan/users.yaml
nonebot_plugin_bilifan/utils.py
nonebot_plugin_bilifan/login/__init__.py
nonebot_plugin_bilifan/src/__init__.py
nonebot_plugin_bilifan/src/api.py
nonebot_plugin_bilifan/src/user.py
nonebot_plugin_bilifan-0.5.0.dist-info/METADATA
nonebot_plugin_bilifan-0.5.0.dist-info/WHEEL
nonebot_plugin_bilifan-0.5.0.dist-info/entry_points.txt
nonebot_plugin_bilifan-0.5.0.dist-info/licenses/LICENSE
nonebot_plugin_bilifan-0.5.0.dist-info/RECORD
