Metadata-Version: 2.4
Name: nonebot_plugin_bilifan
Version: 0.5.0
Summary: 刷站粉丝牌子的机器人插件
Project-URL: homepage, https://github.com/Agnes4m/nonebot_plugin_bilifan
Author-email: Agnes_Digital <Z735803792@163.com>
License: GPLv3
License-File: LICENSE
Keywords: bilibili,nonebot2,plugin
Classifier: License :: OSI Approved :: GNU General Public License v3 (GPLv3)
Classifier: Operating System :: OS Independent
Classifier: Programming Language :: Python
Classifier: Programming Language :: Python :: 3
Classifier: Programming Language :: Python :: 3.9
Classifier: Programming Language :: Python :: 3.10
Classifier: Programming Language :: Python :: 3.11
Classifier: Programming Language :: Python :: 3.12
Requires-Python: <4.0,>=3.9
Requires-Dist: aiohttp-socks>=0.8.0
Requires-Dist: anyio>=4.6.2
Requires-Dist: nonebot-adapter-onebot>=2.2.5
Requires-Dist: nonebot-plugin-alconna>=0.50.0
Requires-Dist: nonebot-plugin-apscheduler>=0.3.0
Requires-Dist: nonebot2>=2.1.0
Requires-Dist: pillow>=10.0.0
Requires-Dist: pyyaml>=6.0
Requires-Dist: qrcode>=7.4.2
